[
  {
    "baseRefName": "main",
    "headRefName": "issue-27-05a03800b7e1",
    "mergedAt": "2026-04-24T11:07:38Z",
    "number": 28,
    "title": "fix: handle repository name collisions without false public success",
    "url": "https://github.com/link-foundation/gh-upload-log/pull/28"
  },
  {
    "baseRefName": "main",
    "headRefName": "issue-23-2dadf4f7942d",
    "mergedAt": "2026-03-28T22:20:54Z",
    "number": 26,
    "title": "feat: handle ENOSPC errors gracefully with actionable error messages",
    "url": "https://github.com/link-foundation/gh-upload-log/pull/26"
  },
  {
    "baseRefName": "main",
    "headRefName": "issue-24-35267d64e3f2",
    "mergedAt": "2026-03-28T21:54:27Z",
    "number": 25,
    "title": "fix: fail early with clean error when file does not exist",
    "url": "https://github.com/link-foundation/gh-upload-log/pull/25"
  },
  {
    "baseRefName": "main",
    "headRefName": "issue-21-939659c74a08",
    "mergedAt": "2026-01-27T12:32:23Z",
    "number": 22,
    "title": "feat: Add direct raw file URL for single-file uploads",
    "url": "https://github.com/link-foundation/gh-upload-log/pull/22"
  },
  {
    "baseRefName": "main",
    "headRefName": "issue-19-d21156abf8ff",
    "mergedAt": "2026-01-06T23:51:24Z",
    "number": 20,
    "title": "fix: Handle HTTP 502 errors for large gist uploads",
    "url": "https://github.com/link-foundation/gh-upload-log/pull/20"
  },
  {
    "baseRefName": "main",
    "headRefName": "issue-17-bafdd945b504",
    "mergedAt": "2025-12-26T19:47:46Z",
    "number": 18,
    "title": "feat: Add NPM badge to README.md",
    "url": "https://github.com/link-foundation/gh-upload-log/pull/18"
  },
  {
    "baseRefName": "main",
    "headRefName": "issue-15-0860073f9eb0",
    "mergedAt": "2025-12-25T14:30:01Z",
    "number": 16,
    "title": "feat: Make output more user friendly with emojis and cleaner format",
    "url": "https://github.com/link-foundation/gh-upload-log/pull/16"
  },
  {
    "baseRefName": "main",
    "headRefName": "issue-13-24bbeb1aa441",
    "mergedAt": "2025-12-25T12:12:04Z",
    "number": 14,
    "title": "fix: Gist URL capture and human-readable file size display",
    "url": "https://github.com/link-foundation/gh-upload-log/pull/14"
  },
  {
    "baseRefName": "main",
    "headRefName": "issue-11-d070e41c43c5",
    "mergedAt": "2025-12-25T11:04:46Z",
    "number": 12,
    "title": "feat: Make repository Bun-only",
    "url": "https://github.com/link-foundation/gh-upload-log/pull/12"
  },
  {
    "baseRefName": "main",
    "headRefName": "issue-9-2b44c0b9a3a0",
    "mergedAt": "2025-12-25T08:52:28Z",
    "number": 10,
    "title": "feat: Complete template feature alignment with manual release support",
    "url": "https://github.com/link-foundation/gh-upload-log/pull/10"
  }
]
